{
  "/component/angular-local-storage.js": 2564784117,
  "/component/angular.js": 1027236094,
  "/component/bootstrap.js": 3187913616,
  "/component/debug.js": 369916937,
  "/component/jquery.js": 249803809,
  "/component/lodash.js": 3138164169,
  "/component/sha1.js": 1503762323,
  "/js/directive.js": 549065187,
  "/js/etcd.js": 3274165754,
  "/js/global.js": 166014621,
  "/js/home.js": 3404923481,
  "/merge/angular-local-storage,sha1,const,http-log,debug,user,directive,global,home.js": 1530715981,
  "/merge/angular-local-storage,sha1,const,http-log,debug,user,directive,util,global,etcd.js": 800048012,
  "/service/const.js": 1426832097,
  "/service/debug.js": 2427906526,
  "/service/http-log.js": 1861769200,
  "/service/user.js": 1816851010,
  "/service/util.js": 4059786890,
  "/component/bootstrap.css": 3763744679,
  "/css/constant.css": 0,
  "/css/etcd.css": 2455072170,
  "/css/global.css": 2208031993,
  "/css/home.css": 902017738,
  "/css/nav.css": 4120812998,
  "/css/widget.css": 1604798757,
  "/merge/global,nav,etcd.css": 4290027461,
  "/merge/global,nav,home.css": 1982594396,
  "/img/raise.png": 3916843176,
  "/pic/raise.png": 3916843176
}